pulpcore/__init__.py
pulpcore/client/__init__.py
pulpcore/client/pulp_npm/__init__.py
pulpcore/client/pulp_npm/api_client.py
pulpcore/client/pulp_npm/api_response.py
pulpcore/client/pulp_npm/configuration.py
pulpcore/client/pulp_npm/exceptions.py
pulpcore/client/pulp_npm/py.typed
pulpcore/client/pulp_npm/rest.py
pulpcore/client/pulp_npm/api/__init__.py
pulpcore/client/pulp_npm/api/content_packages_api.py
pulpcore/client/pulp_npm/api/distributions_npm_api.py
pulpcore/client/pulp_npm/api/remotes_npm_api.py
pulpcore/client/pulp_npm/api/repositories_npm_api.py
pulpcore/client/pulp_npm/api/repositories_npm_versions_api.py
pulpcore/client/pulp_npm/models/__init__.py
pulpcore/client/pulp_npm/models/async_operation_response.py
pulpcore/client/pulp_npm/models/content_summary_response.py
pulpcore/client/pulp_npm/models/npm_npm_distribution.py
pulpcore/client/pulp_npm/models/npm_npm_distribution_response.py
pulpcore/client/pulp_npm/models/npm_npm_remote.py
pulpcore/client/pulp_npm/models/npm_npm_remote_response.py
pulpcore/client/pulp_npm/models/npm_npm_remote_response_hidden_fields_inner.py
pulpcore/client/pulp_npm/models/npm_npm_repository.py
pulpcore/client/pulp_npm/models/npm_npm_repository_response.py
pulpcore/client/pulp_npm/models/npm_package_response.py
pulpcore/client/pulp_npm/models/paginated_repository_version_response_list.py
pulpcore/client/pulp_npm/models/paginatednpm_npm_distribution_response_list.py
pulpcore/client/pulp_npm/models/paginatednpm_npm_remote_response_list.py
pulpcore/client/pulp_npm/models/paginatednpm_npm_repository_response_list.py
pulpcore/client/pulp_npm/models/paginatednpm_package_response_list.py
pulpcore/client/pulp_npm/models/patchednpm_npm_distribution.py
pulpcore/client/pulp_npm/models/patchednpm_npm_remote.py
pulpcore/client/pulp_npm/models/patchednpm_npm_repository.py
pulpcore/client/pulp_npm/models/policy_enum.py
pulpcore/client/pulp_npm/models/repair.py
pulpcore/client/pulp_npm/models/repository_add_remove_content.py
crc_pulp_npm_client-20251023.3.dist-info/METADATA
crc_pulp_npm_client-20251023.3.dist-info/WHEEL
crc_pulp_npm_client-20251023.3.dist-info/top_level.txt
crc_pulp_npm_client-20251023.3.dist-info/RECORD
